{"layers": [{"source": "precomputed://gs://lee-lab_female-adult-nerve-cord/alignmentV4/em/rechunked", "type": "image", "blend": "default", "shaderControls": {}, "name": "FANC EM"}, {"type": "segmentation", "mesh": "precomputed://gs://lee-lab_female-adult-nerve-cord/meshes/FANC/FANC_neurons/meshes", "selectedAlpha": 0.4, "colorSeed": 3788587020, "segments": ["648518346496708653", "648518346492999344", "648518346494727669", "648518346517551652", "648518346483246156", "648518346509739322", "648518346479838358", "648518346507246623", "648518346484612867", "648518346515252039", "648518346499428583", "648518346483250764", "648518346488651192", "648518346496731394", "648518346494135353", "648518346500879516", "648518346491598760", "648518346490340874", "648518346478946256", "648518346494047264", "648518346507277855", "648518346494758819", "648518346483012838"], "skeletonRendering": {"mode2d": "lines_and_points", "mode3d": "lines"}, "name": "6B_local"}, {"type": "segmentation", "mesh": "precomputed://gs://lee-lab_female-adult-nerve-cord/alignmentV4/volume_meshes/meshes", "objectAlpha": 0.1, "hideSegmentZero": false, "ignoreSegmentInteractions": true, "segmentColors": {"1": "#bfbfbf", "2": "#d343d6"}, "segments": ["1", "2"], "skeletonRendering": {"mode2d": "lines_and_points", "mode3d": "lines"}, "name": "region outlines"}], "navigation": {"pose": {"position": {"voxelSize": [4.300000190734863, 4.300000190734863, 45], "voxelCoordinates": [38734, 148426, 2200]}}, "zoomFactor": 12}, "showAxisLines": false, "showDefaultAnnotations": false, "perspectiveZoom": 7000, "showSlices": false, "gpuMemoryLimit": 4000000000, "systemMemoryLimit": 4000000000, "concurrentDownloads": 64, "jsonStateServer": "https://global.daf-apis.com/nglstate/api/v1/post", "selectedLayer": {"layer": "published FANC neurons", "visible": true}, "layout": "3d"}